intentgraph/__init__.py
intentgraph/cli.py
intentgraph/adapters/__init__.py
intentgraph/adapters/file_repository.py
intentgraph/adapters/git.py
intentgraph/adapters/output.py
intentgraph/adapters/parsers/__init__.py
intentgraph/adapters/parsers/base.py
intentgraph/adapters/parsers/enhanced_python_parser.py
intentgraph/adapters/parsers/go_parser.py
intentgraph/adapters/parsers/javascript_parser.py
intentgraph/adapters/parsers/python_parser.py
intentgraph/adapters/parsers/typescript_parser.py
intentgraph/application/__init__.py
intentgraph/application/analyzer.py
intentgraph/application/clustering.py
intentgraph/application/services.py
intentgraph/application/streaming_analyzer.py
intentgraph/domain/__init__.py
intentgraph/domain/clustering.py
intentgraph/domain/exceptions.py
intentgraph/domain/graph.py
intentgraph/domain/models.py
intentgraph-0.2.2.dist-info/METADATA
intentgraph-0.2.2.dist-info/WHEEL
intentgraph-0.2.2.dist-info/entry_points.txt
intentgraph-0.2.2.dist-info/licenses/LICENSE
intentgraph-0.2.2.dist-info/licenses/NOTICE
intentgraph-0.2.2.dist-info/RECORD
