Metadata-Version: 2.4
Name: intentgraph
Version: 0.2.2
Summary: AI-optimized codebase intelligence with intelligent clustering and token-limit friendly output
Project-URL: Documentation, https://github.com/intentgraph/intentgraph
Project-URL: Issues, https://github.com/intentgraph/intentgraph/issues
Project-URL: Source, https://github.com/intentgraph/intentgraph
Author-email: IntentGraph Team <security@intentgraph.dev>
License: MIT
License-File: LICENSE
License-File: NOTICE
Keywords: agents,ai,analysis,clustering,code,codebase-intelligence,dependency,graph,navigation,repository,token-limit
Classifier: Development Status :: 4 - Beta
Classifier: Intended Audience :: Developers
Classifier: License :: OSI Approved :: MIT License
Classifier: Programming Language :: Python :: 3
Classifier: Programming Language :: Python :: 3.12
Classifier: Programming Language :: Python :: 3.13
Classifier: Topic :: Scientific/Engineering :: Artificial Intelligence
Classifier: Topic :: Software Development :: Libraries :: Python Modules
Classifier: Topic :: Software Development :: Quality Assurance
Requires-Python: >=3.12
Requires-Dist: click<9.0.0,>=8.0.0
Requires-Dist: gitpython<4.0.0,>=3.1.41
Requires-Dist: grimp<4.0.0,>=3.3.0
Requires-Dist: networkx<4.0.0,>=3.2.0
Requires-Dist: orjson<4.0.0,>=3.9.0
Requires-Dist: pathspec<1.0.0,>=0.12.0
Requires-Dist: pydantic<3.0.0,>=2.5.0
Requires-Dist: rich<14.0.0,>=13.7.0
Requires-Dist: tree-sitter-language-pack<1.0.0,>=0.8.0
Requires-Dist: typer<1.0.0,>=0.12.0
Provides-Extra: dev
Requires-Dist: bandit>=1.7.5; extra == 'dev'
Requires-Dist: diagrams>=0.23.0; extra == 'dev'
Requires-Dist: hypothesis>=6.92.0; extra == 'dev'
Requires-Dist: mkdocs-material>=9.5.0; extra == 'dev'
Requires-Dist: mypy>=1.8.0; extra == 'dev'
Requires-Dist: pyinstrument>=4.6.0; extra == 'dev'
Requires-Dist: pytest-asyncio>=0.23.0; extra == 'dev'
Requires-Dist: pytest-cov>=4.1.0; extra == 'dev'
Requires-Dist: pytest>=7.4.0; extra == 'dev'
Requires-Dist: ruff>=0.1.9; extra == 'dev'
